pygenometracks/__init__.py
pygenometracks/getAllDefaultsAndPossible.py
pygenometracks/makeTracksFile.py
pygenometracks/plotTracks.py
pygenometracks/readBed.py
pygenometracks/readGtf.py
pygenometracks/tracksClass.py
pygenometracks/utilities.py
pygenometracks/tracks/BedGraphMatrixTrack.py
pygenometracks/tracks/BedGraphTrack.py
pygenometracks/tracks/BedTrack.py
pygenometracks/tracks/BigWigTrack.py
pygenometracks/tracks/EpilogosTrack.py
pygenometracks/tracks/FastaTrack.py
pygenometracks/tracks/GenomeTrack.py
pygenometracks/tracks/GtfTrack.py
pygenometracks/tracks/HLinesTrack.py
pygenometracks/tracks/HiCMatrixLikeTrack.py
pygenometracks/tracks/HiCMatrixSquareTrack.py
pygenometracks/tracks/HiCMatrixTrack.py
pygenometracks/tracks/LinksTrack.py
pygenometracks/tracks/MafTrack.py
pygenometracks/tracks/NarrowPeakTrack.py
pygenometracks/tracks/ScaleBarTrack.py
pygenometracks/tracks/TADsTrack.py
pygenometracks/tracks/__init__.py
pyGenomeTracks-3.9.dist-info/LICENSE
pyGenomeTracks-3.9.dist-info/METADATA
pyGenomeTracks-3.9.dist-info/WHEEL
pyGenomeTracks-3.9.dist-info/entry_points.txt
pyGenomeTracks-3.9.dist-info/top_level.txt
pyGenomeTracks-3.9.dist-info/RECORD
