Metadata-Version: 2.1
Name: pyGenomeTracks
Version: 3.9
Summary: Command-line tool to make beautiful and reproducible genome browser snapshots
Author-email: "Lucille Lopez-Delisle, Leily Rabbani, Joachim Wolf, Björn Grüning" <lucille.delisle@epfl.ch>
License: GNU GENERAL PUBLIC LICENSE
Project-URL: Homepage, https://github.com/deeptools/pyGenomeTracks
Project-URL: Documentation, https://pygenometracks.readthedocs.io
Project-URL: Issues, https://github.com/deeptools/pyGenomeTracks/issues
Classifier: Intended Audience :: Science/Research
Classifier: Topic :: Scientific/Engineering :: Bio-Informatics
Requires-Python: <4,>=3.8
License-File: LICENSE
Requires-Dist: numpy >=1.20
Requires-Dist: matplotlib <3.9,>=3.1.1
Requires-Dist: intervaltree >=2.1.0
Requires-Dist: pyBigWig >=0.3.16
Requires-Dist: future >=0.17.0
Requires-Dist: hicmatrix >=15
Requires-Dist: pysam >=0.14
Requires-Dist: pytest
Requires-Dist: gffutils >=0.9
Requires-Dist: pybedtools >=0.8.1
Requires-Dist: tqdm >=4.20
Requires-Dist: bx-python >=0.8.13
Requires-Dist: pyfaidx >=0.1.3
